django_revolution/__init__.py
django_revolution/app_config.py
django_revolution/apps.py
django_revolution/cli.py
django_revolution/config.py
django_revolution/core_config.py
django_revolution/urls_integration.py
django_revolution/utils.py
django_revolution/zones.py
django_revolution/generators/__init__.py
django_revolution/generators/modern_generator.py
django_revolution/management/__init__.py
django_revolution/management/commands/__init__.py
django_revolution/management/commands/revolution.py
django_revolution/openapi/__init__.py
django_revolution/openapi/archive_manager.py
django_revolution/openapi/generator.py
django_revolution/openapi/heyapi_ts.py
django_revolution/openapi/python_client.py
django_revolution/openapi/schema_postprocessor.py
django_revolution/openapi/utils.py
django_revolution/openapi/templates/README.md
django_revolution/openapi/templates/python/__init__.py.j2
django_revolution/openapi/templates/python/apiconfig_pydantic_2.jinja2
django_revolution/openapi/templates/python/httpx.jinja2
django_revolution/openapi/templates/typescript/index.ts.j2
django_revolution/openapi/templates/typescript/index_consolidated.ts.j2
django_revolution/openapi/templates/typescript/index_group.ts.j2
django_revolution/openapi/templates/typescript/package.json.j2
django_revolution/README.md
django_revolution/pyproject.toml
django_revolution-1.0.46.dist-info/METADATA
django_revolution-1.0.46.dist-info/WHEEL
django_revolution-1.0.46.dist-info/licenses/LICENSE
django_revolution-1.0.46.dist-info/RECORD
