Metadata-Version: 2.4
Name: django-revolution
Version: 1.0.46
Summary: 🚀 OpenAPI client generation framework for Django - Auto-generated TypeScript & Python clients, Zone-based API architecture
Project-URL: Homepage, https://djangocfg.com
Project-URL: Documentation, https://djangocfg.com/docs/features/api-generation
Project-URL: Quick Start, https://djangocfg.com/docs/features/api-generation/quick-start
Project-URL: Live Demo, http://demo.djangocfg.com
Project-URL: Repository, https://github.com/markolofsen/django-revolution
Project-URL: Issues, https://github.com/markolofsen/django-revolution/issues
Project-URL: Django-CFG Framework, https://github.com/markolofsen/django-cfg
Author-email: Django-CFG Team <info@djangocfg.com>
Maintainer-email: Django-CFG Team <info@djangocfg.com>
License: MIT
License-File: LICENSE
Keywords: api,api-client,client,django,drf-spectacular,generation,openapi,openapi-generator,python,python-client,rest,typescript,typescript-client,zones
Classifier: Development Status :: 5 - Production/Stable
Classifier: Framework :: Django
Classifier: Framework :: Django :: 3.2
Classifier: Framework :: Django :: 4.0
Classifier: Framework :: Django :: 4.1
Classifier: Framework :: Django :: 4.2
Classifier: Framework :: Django :: 5.0
Classifier: Intended Audience :: Developers
Classifier: License :: OSI Approved :: MIT License
Classifier: Operating System :: OS Independent
Classifier: Programming Language :: Python
Classifier: Programming Language :: Python :: 3
Classifier: Programming Language :: Python :: 3.10
Classifier: Programming Language :: Python :: 3.11
Classifier: Programming Language :: Python :: 3.12
Classifier: Programming Language :: Python :: 3.13
Classifier: Topic :: Internet :: WWW/HTTP
Classifier: Topic :: Internet :: WWW/HTTP :: Dynamic Content
Classifier: Topic :: Software Development :: Code Generators
Classifier: Topic :: Software Development :: Libraries :: Python Modules
Classifier: Typing :: Typed
Requires-Python: <4.0,>=3.10
Requires-Dist: click>=8.0.0
Requires-Dist: django>=3.2
Requires-Dist: djangorestframework>=3.12.0
Requires-Dist: drf-spectacular>=0.24.0
Requires-Dist: jinja2>=3.0.0
Requires-Dist: openapi-python-client<0.27.0,>=0.26.1
Requires-Dist: pydantic-settings>=2.0.0
Requires-Dist: pydantic>=2.0.0
Requires-Dist: pyyaml>=6.0
Requires-Dist: rich>=13.0.0
Provides-Extra: dev
Requires-Dist: black>=21.0; extra == 'dev'
Requires-Dist: build>=1.0.0; extra == 'dev'
Requires-Dist: isort>=5.0; extra == 'dev'
Requires-Dist: mypy>=0.800; extra == 'dev'
Requires-Dist: pytest-django>=4.0; extra == 'dev'
Requires-Dist: pytest>=6.0; extra == 'dev'
Requires-Dist: toml>=0.10.0; extra == 'dev'
Requires-Dist: twine>=4.0.0; extra == 'dev'
Provides-Extra: formatting
Requires-Dist: black>=21.0; extra == 'formatting'
Requires-Dist: isort>=5.0; extra == 'formatting'
Provides-Extra: test
Requires-Dist: pytest-django>=4.0; extra == 'test'
Requires-Dist: pytest>=6.0; extra == 'test'
